<?xml version="1.0" encoding="UTF-8" standalone="no"?>
<entity name="localMin">
  <port name="sad_in0">
    <property name="direction" value="in"/>
    <property name="mathtype" value="real"/>
    <property name="datatype" value="int"/>
    <property name="tokentype" value="vector">
    	<property name="dim0" value="82"/>
    </property>
  </port>
  <port name="sad_in1">
    <property name="direction" value="in"/>
    <property name="mathtype" value="real"/>
    <property name="datatype" value="int"/>
    <property name="tokentype" value="vector">
    	<property name="dim0" value="82"/>
    </property>
  </port>
  <port name="sad_in2">
    <property name="direction" value="in"/>
    <property name="mathtype" value="real"/>
    <property name="datatype" value="int"/>
    <property name="tokentype" value="vector">
    	<property name="dim0" value="82"/>
    </property>
  </port>
  <port name="sad_in3">
    <property name="direction" value="in"/>
    <property name="mathtype" value="real"/>
    <property name="datatype" value="int"/>
    <property name="tokentype" value="vector">
    	<property name="dim0" value="82"/>
    </property>
  </port>
  <port name="sad_in4">
    <property name="direction" value="in"/>
    <property name="mathtype" value="real"/>
    <property name="datatype" value="int"/>
    <property name="tokentype" value="vector">
    	<property name="dim0" value="82"/>
    </property>
  </port>
  <port name="sad_in5">
    <property name="direction" value="in"/>
    <property name="mathtype" value="real"/>
    <property name="datatype" value="int"/>
    <property name="tokentype" value="vector">
    	<property name="dim0" value="82"/>
    </property>
  </port>
  <port name="sad_in6">
    <property name="direction" value="in"/>
    <property name="mathtype" value="real"/>
    <property name="datatype" value="int"/>
    <property name="tokentype" value="vector">
    	<property name="dim0" value="82"/>
    </property>
  </port>
  <port name="sad_in7">
    <property name="direction" value="in"/>
    <property name="mathtype" value="real"/>
    <property name="datatype" value="int"/>
    <property name="tokentype" value="vector">
    	<property name="dim0" value="82"/>
    </property>
  </port>
  <port name="sad_in8">
    <property name="direction" value="in"/>
    <property name="mathtype" value="real"/>
    <property name="datatype" value="int"/>
    <property name="tokentype" value="vector">
    	<property name="dim0" value="82"/>
    </property>
  </port>
  <port name="sad_in9">
    <property name="direction" value="in"/>
    <property name="mathtype" value="real"/>
    <property name="datatype" value="int"/>
    <property name="tokentype" value="vector">
    	<property name="dim0" value="82"/>
    </property>
  </port>
  <port name="sad_in10">
    <property name="direction" value="in"/>
    <property name="mathtype" value="real"/>
    <property name="datatype" value="int"/>
    <property name="tokentype" value="vector">
    	<property name="dim0" value="82"/>
    </property>
  </port>
  <port name="sad_in11">
    <property name="direction" value="in"/>
    <property name="mathtype" value="real"/>
    <property name="datatype" value="int"/>
    <property name="tokentype" value="vector">
    	<property name="dim0" value="82"/>
    </property>
  </port>
  <port name="sad_in12">
    <property name="direction" value="in"/>
    <property name="mathtype" value="real"/>
    <property name="datatype" value="int"/>
    <property name="tokentype" value="vector">
    	<property name="dim0" value="82"/>
    </property>
  </port>
  <port name="sad_in13">
    <property name="direction" value="in"/>
    <property name="mathtype" value="real"/>
    <property name="datatype" value="int"/>
    <property name="tokentype" value="vector">
    	<property name="dim0" value="82"/>
    </property>
  </port>
  <port name="sad_in14">
    <property name="direction" value="in"/>
    <property name="mathtype" value="real"/>
    <property name="datatype" value="int"/>
    <property name="tokentype" value="vector">
    	<property name="dim0" value="82"/>
    </property>
  </port>
  <port name="sad_in15">
    <property name="direction" value="in"/>
    <property name="mathtype" value="real"/>
    <property name="datatype" value="int"/>
    <property name="tokentype" value="vector">
    	<property name="dim0" value="82"/>
    </property>
  </port>
  <port name="sad_in16">
    <property name="direction" value="in"/>
    <property name="mathtype" value="real"/>
    <property name="datatype" value="int"/>
    <property name="tokentype" value="vector">
    	<property name="dim0" value="82"/>
    </property>
  </port>
  <port name="sad_in17">
    <property name="direction" value="in"/>
    <property name="mathtype" value="real"/>
    <property name="datatype" value="int"/>
    <property name="tokentype" value="vector">
    	<property name="dim0" value="82"/>
    </property>
  </port>
  <port name="sad_in18">
    <property name="direction" value="in"/>
    <property name="mathtype" value="real"/>
    <property name="datatype" value="int"/>
    <property name="tokentype" value="vector">
    	<property name="dim0" value="82"/>
    </property>
  </port>
  <port name="sad_in19">
    <property name="direction" value="in"/>
    <property name="mathtype" value="real"/>
    <property name="datatype" value="int"/>
    <property name="tokentype" value="vector">
    	<property name="dim0" value="82"/>
    </property>
  </port>
  <port name="sad_in20">
    <property name="direction" value="in"/>
    <property name="mathtype" value="real"/>
    <property name="datatype" value="int"/>
    <property name="tokentype" value="vector">
    	<property name="dim0" value="82"/>
    </property>
  </port>
  <port name="sad_in21">
    <property name="direction" value="in"/>
    <property name="mathtype" value="real"/>
    <property name="datatype" value="int"/>
    <property name="tokentype" value="vector">
    	<property name="dim0" value="82"/>
    </property>
  </port>
  <port name="sad_in22">
    <property name="direction" value="in"/>
    <property name="mathtype" value="real"/>
    <property name="datatype" value="int"/>
    <property name="tokentype" value="vector">
    	<property name="dim0" value="82"/>
    </property>
  </port>
  <port name="sad_in23">
    <property name="direction" value="in"/>
    <property name="mathtype" value="real"/>
    <property name="datatype" value="int"/>
    <property name="tokentype" value="vector">
    	<property name="dim0" value="82"/>
    </property>
  </port>
  <port name="sad_in24">
    <property name="direction" value="in"/>
    <property name="mathtype" value="real"/>
    <property name="datatype" value="int"/>
    <property name="tokentype" value="vector">
    	<property name="dim0" value="82"/>
    </property>
  </port>
  <port name="sad_in25">
    <property name="direction" value="in"/>
    <property name="mathtype" value="real"/>
    <property name="datatype" value="int"/>
    <property name="tokentype" value="vector">
    	<property name="dim0" value="82"/>
    </property>
  </port>
  <port name="sad_in26">
    <property name="direction" value="in"/>
    <property name="mathtype" value="real"/>
    <property name="datatype" value="int"/>
    <property name="tokentype" value="vector">
    	<property name="dim0" value="82"/>
    </property>
  </port>
  <port name="sad_in27">
    <property name="direction" value="in"/>
    <property name="mathtype" value="real"/>
    <property name="datatype" value="int"/>
    <property name="tokentype" value="vector">
    	<property name="dim0" value="82"/>
    </property>
  </port>
  <port name="sad_in28">
    <property name="direction" value="in"/>
    <property name="mathtype" value="real"/>
    <property name="datatype" value="int"/>
    <property name="tokentype" value="vector">
    	<property name="dim0" value="82"/>
    </property>
  </port>
  <port name="sad_in29">
    <property name="direction" value="in"/>
    <property name="mathtype" value="real"/>
    <property name="datatype" value="int"/>
    <property name="tokentype" value="vector">
    	<property name="dim0" value="82"/>
    </property>
  </port>
  <port name="sad_in30">
    <property name="direction" value="in"/>
    <property name="mathtype" value="real"/>
    <property name="datatype" value="int"/>
    <property name="tokentype" value="vector">
    	<property name="dim0" value="82"/>
    </property>
  </port>
  <port name="sad_in31">
    <property name="direction" value="in"/>
    <property name="mathtype" value="real"/>
    <property name="datatype" value="int"/>
    <property name="tokentype" value="vector">
    	<property name="dim0" value="82"/>
    </property>
  </port>
  <port name="localminsad_out">
    <property name="direction" value="out"/>
    <property name="mathtype" value="real"/>
    <property name="datatype" value="int"/>
    <property name="tokentype" value="vector">
    	<property name="dim0" value="82"/>
    </property>
  </port>
</entity>