<?xml version="1.0" encoding="UTF-8" standalone="no"?>
<entity name="Processor_2">
  <constructure>
    <property class="" name="director"/>
    <entity class="xmlfiles.FSD_44_16QAM.result.P2_2.pefiles.PE_2_1" name="PE_2_1"/>
    <relation cost="1" name="Edge_1"/>
    <link port="PE_2_1_Ele_in1" relation="Edge_1"/>
    <link port="PE_2_1.Ele_in1" relation="Edge_1"/>
    <relation cost="2" name="Edge_2"/>
    <link port="PE_2_1_Ele_in2" relation="Edge_2"/>
    <link port="PE_2_1.Ele_in2" relation="Edge_2"/>
    <relation cost="2" name="Edge_3"/>
    <link port="PE_2_1_Ele_in3" relation="Edge_3"/>
    <link port="PE_2_1.Ele_in3" relation="Edge_3"/>
    <relation cost="2" name="Edge_4"/>
    <link port="PE_2_1_Ele_in4" relation="Edge_4"/>
    <link port="PE_2_1.Ele_in4" relation="Edge_4"/>
    <relation cost="2" name="Edge_5"/>
    <link port="PE_2_1_Ele_in5" relation="Edge_5"/>
    <link port="PE_2_1.Ele_in5" relation="Edge_5"/>
    <relation cost="1" name="Edge_6"/>
    <link port="PE_2_1_Ele_in12" relation="Edge_6"/>
    <link port="PE_2_1.Ele_in12" relation="Edge_6"/>
    <relation cost="2" name="Edge_7"/>
    <link port="PE_2_1_Ele_in22" relation="Edge_7"/>
    <link port="PE_2_1.Ele_in22" relation="Edge_7"/>
    <relation cost="2" name="Edge_8"/>
    <link port="PE_2_1_Ele_in32" relation="Edge_8"/>
    <link port="PE_2_1.Ele_in32" relation="Edge_8"/>
    <relation cost="2" name="Edge_9"/>
    <link port="PE_2_1_Ele_in42" relation="Edge_9"/>
    <link port="PE_2_1.Ele_in42" relation="Edge_9"/>
    <relation cost="2" name="Edge_10"/>
    <link port="PE_2_1_Ele_in52" relation="Edge_10"/>
    <link port="PE_2_1.Ele_in52" relation="Edge_10"/>
    <relation cost="1" name="Edge_11"/>
    <link port="PE_2_1_Ele_in13" relation="Edge_11"/>
    <link port="PE_2_1.Ele_in13" relation="Edge_11"/>
    <relation cost="2" name="Edge_12"/>
    <link port="PE_2_1_Ele_in23" relation="Edge_12"/>
    <link port="PE_2_1.Ele_in23" relation="Edge_12"/>
    <relation cost="2" name="Edge_13"/>
    <link port="PE_2_1_Ele_in33" relation="Edge_13"/>
    <link port="PE_2_1.Ele_in33" relation="Edge_13"/>
    <relation cost="2" name="Edge_14"/>
    <link port="PE_2_1_Ele_in43" relation="Edge_14"/>
    <link port="PE_2_1.Ele_in43" relation="Edge_14"/>
    <relation cost="2" name="Edge_15"/>
    <link port="PE_2_1_Ele_in53" relation="Edge_15"/>
    <link port="PE_2_1.Ele_in53" relation="Edge_15"/>
    <relation cost="1" name="Edge_16"/>
    <link port="PE_2_1_Ele_in14" relation="Edge_16"/>
    <link port="PE_2_1.Ele_in14" relation="Edge_16"/>
    <relation cost="2" name="Edge_17"/>
    <link port="PE_2_1_Ele_in24" relation="Edge_17"/>
    <link port="PE_2_1.Ele_in24" relation="Edge_17"/>
    <relation cost="2" name="Edge_18"/>
    <link port="PE_2_1_Ele_in34" relation="Edge_18"/>
    <link port="PE_2_1.Ele_in34" relation="Edge_18"/>
    <relation cost="2" name="Edge_19"/>
    <link port="PE_2_1_Ele_in44" relation="Edge_19"/>
    <link port="PE_2_1.Ele_in44" relation="Edge_19"/>
    <relation cost="2" name="Edge_20"/>
    <link port="PE_2_1_Ele_in54" relation="Edge_20"/>
    <link port="PE_2_1.Ele_in54" relation="Edge_20"/>
    <relation cost="1" name="Edge_21"/>
    <link port="PE_2_1_Ele_in15" relation="Edge_21"/>
    <link port="PE_2_1.Ele_in15" relation="Edge_21"/>
    <relation cost="2" name="Edge_22"/>
    <link port="PE_2_1_Ele_in25" relation="Edge_22"/>
    <link port="PE_2_1.Ele_in25" relation="Edge_22"/>
    <relation cost="2" name="Edge_23"/>
    <link port="PE_2_1_Ele_in35" relation="Edge_23"/>
    <link port="PE_2_1.Ele_in35" relation="Edge_23"/>
    <relation cost="2" name="Edge_24"/>
    <link port="PE_2_1_Ele_in45" relation="Edge_24"/>
    <link port="PE_2_1.Ele_in45" relation="Edge_24"/>
    <relation cost="2" name="Edge_25"/>
    <link port="PE_2_1_Ele_in55" relation="Edge_25"/>
    <link port="PE_2_1.Ele_in55" relation="Edge_25"/>
    <relation cost="1" name="Edge_26"/>
    <link port="PE_2_1_Ele_in16" relation="Edge_26"/>
    <link port="PE_2_1.Ele_in16" relation="Edge_26"/>
    <relation cost="2" name="Edge_27"/>
    <link port="PE_2_1_Ele_in26" relation="Edge_27"/>
    <link port="PE_2_1.Ele_in26" relation="Edge_27"/>
    <relation cost="2" name="Edge_28"/>
    <link port="PE_2_1_Ele_in36" relation="Edge_28"/>
    <link port="PE_2_1.Ele_in36" relation="Edge_28"/>
    <relation cost="2" name="Edge_29"/>
    <link port="PE_2_1_Ele_in46" relation="Edge_29"/>
    <link port="PE_2_1.Ele_in46" relation="Edge_29"/>
    <relation cost="2" name="Edge_30"/>
    <link port="PE_2_1_Ele_in56" relation="Edge_30"/>
    <link port="PE_2_1.Ele_in56" relation="Edge_30"/>
    <relation cost="1" name="Edge_31"/>
    <link port="PE_2_1_Ele_in17" relation="Edge_31"/>
    <link port="PE_2_1.Ele_in17" relation="Edge_31"/>
    <relation cost="2" name="Edge_32"/>
    <link port="PE_2_1_Ele_in27" relation="Edge_32"/>
    <link port="PE_2_1.Ele_in27" relation="Edge_32"/>
    <relation cost="2" name="Edge_33"/>
    <link port="PE_2_1_Ele_in37" relation="Edge_33"/>
    <link port="PE_2_1.Ele_in37" relation="Edge_33"/>
    <relation cost="2" name="Edge_34"/>
    <link port="PE_2_1_Ele_in47" relation="Edge_34"/>
    <link port="PE_2_1.Ele_in47" relation="Edge_34"/>
    <relation cost="2" name="Edge_35"/>
    <link port="PE_2_1_Ele_in57" relation="Edge_35"/>
    <link port="PE_2_1.Ele_in57" relation="Edge_35"/>
    <relation cost="1" name="Edge_36"/>
    <link port="PE_2_1_Ele_in18" relation="Edge_36"/>
    <link port="PE_2_1.Ele_in18" relation="Edge_36"/>
    <relation cost="2" name="Edge_37"/>
    <link port="PE_2_1_Ele_in28" relation="Edge_37"/>
    <link port="PE_2_1.Ele_in28" relation="Edge_37"/>
    <relation cost="2" name="Edge_38"/>
    <link port="PE_2_1_Ele_in38" relation="Edge_38"/>
    <link port="PE_2_1.Ele_in38" relation="Edge_38"/>
    <relation cost="2" name="Edge_39"/>
    <link port="PE_2_1_Ele_in48" relation="Edge_39"/>
    <link port="PE_2_1.Ele_in48" relation="Edge_39"/>
    <relation cost="2" name="Edge_40"/>
    <link port="PE_2_1_Ele_in58" relation="Edge_40"/>
    <link port="PE_2_1.Ele_in58" relation="Edge_40"/>
    <relation cost="1" name="Edge_41"/>
    <link port="PE_2_1_Ele_in19" relation="Edge_41"/>
    <link port="PE_2_1.Ele_in19" relation="Edge_41"/>
    <relation cost="2" name="Edge_42"/>
    <link port="PE_2_1_Ele_in29" relation="Edge_42"/>
    <link port="PE_2_1.Ele_in29" relation="Edge_42"/>
    <relation cost="2" name="Edge_43"/>
    <link port="PE_2_1_Ele_in39" relation="Edge_43"/>
    <link port="PE_2_1.Ele_in39" relation="Edge_43"/>
    <relation cost="2" name="Edge_44"/>
    <link port="PE_2_1_Ele_in49" relation="Edge_44"/>
    <link port="PE_2_1.Ele_in49" relation="Edge_44"/>
    <relation cost="2" name="Edge_45"/>
    <link port="PE_2_1_Ele_in59" relation="Edge_45"/>
    <link port="PE_2_1.Ele_in59" relation="Edge_45"/>
    <relation cost="1" name="Edge_46"/>
    <link port="PE_2_1_Ele_in110" relation="Edge_46"/>
    <link port="PE_2_1.Ele_in110" relation="Edge_46"/>
    <relation cost="2" name="Edge_47"/>
    <link port="PE_2_1_Ele_in210" relation="Edge_47"/>
    <link port="PE_2_1.Ele_in210" relation="Edge_47"/>
    <relation cost="2" name="Edge_48"/>
    <link port="PE_2_1_Ele_in310" relation="Edge_48"/>
    <link port="PE_2_1.Ele_in310" relation="Edge_48"/>
    <relation cost="2" name="Edge_49"/>
    <link port="PE_2_1_Ele_in410" relation="Edge_49"/>
    <link port="PE_2_1.Ele_in410" relation="Edge_49"/>
    <relation cost="2" name="Edge_50"/>
    <link port="PE_2_1_Ele_in510" relation="Edge_50"/>
    <link port="PE_2_1.Ele_in510" relation="Edge_50"/>
    <relation cost="1" name="Edge_51"/>
    <link port="PE_2_1_Ele_in111" relation="Edge_51"/>
    <link port="PE_2_1.Ele_in111" relation="Edge_51"/>
    <relation cost="2" name="Edge_52"/>
    <link port="PE_2_1_Ele_in211" relation="Edge_52"/>
    <link port="PE_2_1.Ele_in211" relation="Edge_52"/>
    <relation cost="2" name="Edge_53"/>
    <link port="PE_2_1_Ele_in311" relation="Edge_53"/>
    <link port="PE_2_1.Ele_in311" relation="Edge_53"/>
    <relation cost="2" name="Edge_54"/>
    <link port="PE_2_1_Ele_in411" relation="Edge_54"/>
    <link port="PE_2_1.Ele_in411" relation="Edge_54"/>
    <relation cost="2" name="Edge_55"/>
    <link port="PE_2_1_Ele_in511" relation="Edge_55"/>
    <link port="PE_2_1.Ele_in511" relation="Edge_55"/>
    <relation cost="1" name="Edge_56"/>
    <link port="PE_2_1_Ele_in112" relation="Edge_56"/>
    <link port="PE_2_1.Ele_in112" relation="Edge_56"/>
    <relation cost="2" name="Edge_57"/>
    <link port="PE_2_1_Ele_in212" relation="Edge_57"/>
    <link port="PE_2_1.Ele_in212" relation="Edge_57"/>
    <relation cost="2" name="Edge_58"/>
    <link port="PE_2_1_Ele_in312" relation="Edge_58"/>
    <link port="PE_2_1.Ele_in312" relation="Edge_58"/>
    <relation cost="2" name="Edge_59"/>
    <link port="PE_2_1_Ele_in412" relation="Edge_59"/>
    <link port="PE_2_1.Ele_in412" relation="Edge_59"/>
    <relation cost="2" name="Edge_60"/>
    <link port="PE_2_1_Ele_in512" relation="Edge_60"/>
    <link port="PE_2_1.Ele_in512" relation="Edge_60"/>
    <relation cost="1" name="Edge_61"/>
    <link port="PE_2_1_Ele_in113" relation="Edge_61"/>
    <link port="PE_2_1.Ele_in113" relation="Edge_61"/>
    <relation cost="2" name="Edge_62"/>
    <link port="PE_2_1_Ele_in213" relation="Edge_62"/>
    <link port="PE_2_1.Ele_in213" relation="Edge_62"/>
    <relation cost="2" name="Edge_63"/>
    <link port="PE_2_1_Ele_in313" relation="Edge_63"/>
    <link port="PE_2_1.Ele_in313" relation="Edge_63"/>
    <relation cost="2" name="Edge_64"/>
    <link port="PE_2_1_Ele_in413" relation="Edge_64"/>
    <link port="PE_2_1.Ele_in413" relation="Edge_64"/>
    <relation cost="2" name="Edge_65"/>
    <link port="PE_2_1_Ele_in513" relation="Edge_65"/>
    <link port="PE_2_1.Ele_in513" relation="Edge_65"/>
    <relation cost="1" name="Edge_66"/>
    <link port="PE_2_1_Ele_in114" relation="Edge_66"/>
    <link port="PE_2_1.Ele_in114" relation="Edge_66"/>
    <relation cost="2" name="Edge_67"/>
    <link port="PE_2_1_Ele_in214" relation="Edge_67"/>
    <link port="PE_2_1.Ele_in214" relation="Edge_67"/>
    <relation cost="2" name="Edge_68"/>
    <link port="PE_2_1_Ele_in314" relation="Edge_68"/>
    <link port="PE_2_1.Ele_in314" relation="Edge_68"/>
    <relation cost="2" name="Edge_69"/>
    <link port="PE_2_1_Ele_in414" relation="Edge_69"/>
    <link port="PE_2_1.Ele_in414" relation="Edge_69"/>
    <relation cost="2" name="Edge_70"/>
    <link port="PE_2_1_Ele_in514" relation="Edge_70"/>
    <link port="PE_2_1.Ele_in514" relation="Edge_70"/>
    <relation cost="1" name="Edge_71"/>
    <link port="PE_2_1_Ele_in115" relation="Edge_71"/>
    <link port="PE_2_1.Ele_in115" relation="Edge_71"/>
    <relation cost="2" name="Edge_72"/>
    <link port="PE_2_1_Ele_in215" relation="Edge_72"/>
    <link port="PE_2_1.Ele_in215" relation="Edge_72"/>
    <relation cost="2" name="Edge_73"/>
    <link port="PE_2_1_Ele_in315" relation="Edge_73"/>
    <link port="PE_2_1.Ele_in315" relation="Edge_73"/>
    <relation cost="2" name="Edge_74"/>
    <link port="PE_2_1_Ele_in415" relation="Edge_74"/>
    <link port="PE_2_1.Ele_in415" relation="Edge_74"/>
    <relation cost="2" name="Edge_75"/>
    <link port="PE_2_1_Ele_in515" relation="Edge_75"/>
    <link port="PE_2_1.Ele_in515" relation="Edge_75"/>
    <relation cost="1" name="Edge_76"/>
    <link port="PE_2_1_Ele_in116" relation="Edge_76"/>
    <link port="PE_2_1.Ele_in116" relation="Edge_76"/>
    <relation cost="2" name="Edge_77"/>
    <link port="PE_2_1_Ele_in216" relation="Edge_77"/>
    <link port="PE_2_1.Ele_in216" relation="Edge_77"/>
    <relation cost="2" name="Edge_78"/>
    <link port="PE_2_1_Ele_in316" relation="Edge_78"/>
    <link port="PE_2_1.Ele_in316" relation="Edge_78"/>
    <relation cost="2" name="Edge_79"/>
    <link port="PE_2_1_Ele_in416" relation="Edge_79"/>
    <link port="PE_2_1.Ele_in416" relation="Edge_79"/>
    <relation cost="2" name="Edge_80"/>
    <link port="PE_2_1_Ele_in516" relation="Edge_80"/>
    <link port="PE_2_1.Ele_in516" relation="Edge_80"/>
    <relation cost="1" name="Edge_81"/>
    <link port="PE_2_1_Ele_in11" relation="Edge_81"/>
    <link port="PE_2_1.Ele_in11" relation="Edge_81"/>
    <relation cost="2" name="Edge_82"/>
    <link port="PE_2_1_Ele_in21" relation="Edge_82"/>
    <link port="PE_2_1.Ele_in21" relation="Edge_82"/>
    <relation cost="2" name="Edge_83"/>
    <link port="PE_2_1_Ele_in31" relation="Edge_83"/>
    <link port="PE_2_1.Ele_in31" relation="Edge_83"/>
    <relation cost="2" name="Edge_84"/>
    <link port="PE_2_1_Ele_in41" relation="Edge_84"/>
    <link port="PE_2_1.Ele_in41" relation="Edge_84"/>
    <relation cost="2" name="Edge_85"/>
    <link port="PE_2_1_Ele_in51" relation="Edge_85"/>
    <link port="PE_2_1.Ele_in51" relation="Edge_85"/>
    <relation cost="1" name="Edge_86"/>
    <link port="PE_2_1_Ele_in121" relation="Edge_86"/>
    <link port="PE_2_1.Ele_in121" relation="Edge_86"/>
    <relation cost="2" name="Edge_87"/>
    <link port="PE_2_1_Ele_in221" relation="Edge_87"/>
    <link port="PE_2_1.Ele_in221" relation="Edge_87"/>
    <relation cost="2" name="Edge_88"/>
    <link port="PE_2_1_Ele_in321" relation="Edge_88"/>
    <link port="PE_2_1.Ele_in321" relation="Edge_88"/>
    <relation cost="2" name="Edge_89"/>
    <link port="PE_2_1_Ele_in421" relation="Edge_89"/>
    <link port="PE_2_1.Ele_in421" relation="Edge_89"/>
    <relation cost="2" name="Edge_90"/>
    <link port="PE_2_1_Ele_in521" relation="Edge_90"/>
    <link port="PE_2_1.Ele_in521" relation="Edge_90"/>
    <relation cost="1" name="Edge_91"/>
    <link port="PE_2_1_Ele_in131" relation="Edge_91"/>
    <link port="PE_2_1.Ele_in131" relation="Edge_91"/>
    <relation cost="2" name="Edge_92"/>
    <link port="PE_2_1_Ele_in231" relation="Edge_92"/>
    <link port="PE_2_1.Ele_in231" relation="Edge_92"/>
    <relation cost="2" name="Edge_93"/>
    <link port="PE_2_1_Ele_in331" relation="Edge_93"/>
    <link port="PE_2_1.Ele_in331" relation="Edge_93"/>
    <relation cost="2" name="Edge_94"/>
    <link port="PE_2_1_Ele_in431" relation="Edge_94"/>
    <link port="PE_2_1.Ele_in431" relation="Edge_94"/>
    <relation cost="2" name="Edge_95"/>
    <link port="PE_2_1_Ele_in531" relation="Edge_95"/>
    <link port="PE_2_1.Ele_in531" relation="Edge_95"/>
    <relation cost="1" name="Edge_96"/>
    <link port="PE_2_1_Ele_in141" relation="Edge_96"/>
    <link port="PE_2_1.Ele_in141" relation="Edge_96"/>
    <relation cost="2" name="Edge_97"/>
    <link port="PE_2_1_Ele_in241" relation="Edge_97"/>
    <link port="PE_2_1.Ele_in241" relation="Edge_97"/>
    <relation cost="2" name="Edge_98"/>
    <link port="PE_2_1_Ele_in341" relation="Edge_98"/>
    <link port="PE_2_1.Ele_in341" relation="Edge_98"/>
    <relation cost="2" name="Edge_99"/>
    <link port="PE_2_1_Ele_in441" relation="Edge_99"/>
    <link port="PE_2_1.Ele_in441" relation="Edge_99"/>
    <relation cost="2" name="Edge_100"/>
    <link port="PE_2_1_Ele_in541" relation="Edge_100"/>
    <link port="PE_2_1.Ele_in541" relation="Edge_100"/>
    <relation cost="1" name="Edge_101"/>
    <link port="PE_2_1_Ele_in151" relation="Edge_101"/>
    <link port="PE_2_1.Ele_in151" relation="Edge_101"/>
    <relation cost="2" name="Edge_102"/>
    <link port="PE_2_1_Ele_in251" relation="Edge_102"/>
    <link port="PE_2_1.Ele_in251" relation="Edge_102"/>
    <relation cost="2" name="Edge_103"/>
    <link port="PE_2_1_Ele_in351" relation="Edge_103"/>
    <link port="PE_2_1.Ele_in351" relation="Edge_103"/>
    <relation cost="2" name="Edge_104"/>
    <link port="PE_2_1_Ele_in451" relation="Edge_104"/>
    <link port="PE_2_1.Ele_in451" relation="Edge_104"/>
    <relation cost="2" name="Edge_105"/>
    <link port="PE_2_1_Ele_in551" relation="Edge_105"/>
    <link port="PE_2_1.Ele_in551" relation="Edge_105"/>
    <relation cost="1" name="Edge_106"/>
    <link port="PE_2_1_Ele_in161" relation="Edge_106"/>
    <link port="PE_2_1.Ele_in161" relation="Edge_106"/>
    <relation cost="2" name="Edge_107"/>
    <link port="PE_2_1_Ele_in261" relation="Edge_107"/>
    <link port="PE_2_1.Ele_in261" relation="Edge_107"/>
    <relation cost="2" name="Edge_108"/>
    <link port="PE_2_1_Ele_in361" relation="Edge_108"/>
    <link port="PE_2_1.Ele_in361" relation="Edge_108"/>
    <relation cost="2" name="Edge_109"/>
    <link port="PE_2_1_Ele_in461" relation="Edge_109"/>
    <link port="PE_2_1.Ele_in461" relation="Edge_109"/>
    <relation cost="2" name="Edge_110"/>
    <link port="PE_2_1_Ele_in561" relation="Edge_110"/>
    <link port="PE_2_1.Ele_in561" relation="Edge_110"/>
    <relation cost="1" name="Edge_111"/>
    <link port="PE_2_1_Ele_in171" relation="Edge_111"/>
    <link port="PE_2_1.Ele_in171" relation="Edge_111"/>
    <relation cost="2" name="Edge_112"/>
    <link port="PE_2_1_Ele_in271" relation="Edge_112"/>
    <link port="PE_2_1.Ele_in271" relation="Edge_112"/>
    <relation cost="2" name="Edge_113"/>
    <link port="PE_2_1_Ele_in371" relation="Edge_113"/>
    <link port="PE_2_1.Ele_in371" relation="Edge_113"/>
    <relation cost="2" name="Edge_114"/>
    <link port="PE_2_1_Ele_in471" relation="Edge_114"/>
    <link port="PE_2_1.Ele_in471" relation="Edge_114"/>
    <relation cost="2" name="Edge_115"/>
    <link port="PE_2_1_Ele_in571" relation="Edge_115"/>
    <link port="PE_2_1.Ele_in571" relation="Edge_115"/>
    <relation cost="1" name="Edge_116"/>
    <link port="PE_2_1_Ele_in181" relation="Edge_116"/>
    <link port="PE_2_1.Ele_in181" relation="Edge_116"/>
    <relation cost="2" name="Edge_117"/>
    <link port="PE_2_1_Ele_in281" relation="Edge_117"/>
    <link port="PE_2_1.Ele_in281" relation="Edge_117"/>
    <relation cost="2" name="Edge_118"/>
    <link port="PE_2_1_Ele_in381" relation="Edge_118"/>
    <link port="PE_2_1.Ele_in381" relation="Edge_118"/>
    <relation cost="2" name="Edge_119"/>
    <link port="PE_2_1_Ele_in481" relation="Edge_119"/>
    <link port="PE_2_1.Ele_in481" relation="Edge_119"/>
    <relation cost="2" name="Edge_120"/>
    <link port="PE_2_1_Ele_in581" relation="Edge_120"/>
    <link port="PE_2_1.Ele_in581" relation="Edge_120"/>
    <relation cost="1" name="Edge_121"/>
    <link port="PE_2_1_Ele_in191" relation="Edge_121"/>
    <link port="PE_2_1.Ele_in191" relation="Edge_121"/>
    <relation cost="2" name="Edge_122"/>
    <link port="PE_2_1_Ele_in291" relation="Edge_122"/>
    <link port="PE_2_1.Ele_in291" relation="Edge_122"/>
    <relation cost="2" name="Edge_123"/>
    <link port="PE_2_1_Ele_in391" relation="Edge_123"/>
    <link port="PE_2_1.Ele_in391" relation="Edge_123"/>
    <relation cost="2" name="Edge_124"/>
    <link port="PE_2_1_Ele_in491" relation="Edge_124"/>
    <link port="PE_2_1.Ele_in491" relation="Edge_124"/>
    <relation cost="2" name="Edge_125"/>
    <link port="PE_2_1_Ele_in591" relation="Edge_125"/>
    <link port="PE_2_1.Ele_in591" relation="Edge_125"/>
    <relation cost="1" name="Edge_126"/>
    <link port="PE_2_1_Ele_in1101" relation="Edge_126"/>
    <link port="PE_2_1.Ele_in1101" relation="Edge_126"/>
    <relation cost="2" name="Edge_127"/>
    <link port="PE_2_1_Ele_in2101" relation="Edge_127"/>
    <link port="PE_2_1.Ele_in2101" relation="Edge_127"/>
    <relation cost="2" name="Edge_128"/>
    <link port="PE_2_1_Ele_in3101" relation="Edge_128"/>
    <link port="PE_2_1.Ele_in3101" relation="Edge_128"/>
    <relation cost="2" name="Edge_129"/>
    <link port="PE_2_1_Ele_in4101" relation="Edge_129"/>
    <link port="PE_2_1.Ele_in4101" relation="Edge_129"/>
    <relation cost="2" name="Edge_130"/>
    <link port="PE_2_1_Ele_in5101" relation="Edge_130"/>
    <link port="PE_2_1.Ele_in5101" relation="Edge_130"/>
    <relation cost="1" name="Edge_131"/>
    <link port="PE_2_1_Ele_in1111" relation="Edge_131"/>
    <link port="PE_2_1.Ele_in1111" relation="Edge_131"/>
    <relation cost="2" name="Edge_132"/>
    <link port="PE_2_1_Ele_in2111" relation="Edge_132"/>
    <link port="PE_2_1.Ele_in2111" relation="Edge_132"/>
    <relation cost="2" name="Edge_133"/>
    <link port="PE_2_1_Ele_in3111" relation="Edge_133"/>
    <link port="PE_2_1.Ele_in3111" relation="Edge_133"/>
    <relation cost="2" name="Edge_134"/>
    <link port="PE_2_1_Ele_in4111" relation="Edge_134"/>
    <link port="PE_2_1.Ele_in4111" relation="Edge_134"/>
    <relation cost="2" name="Edge_135"/>
    <link port="PE_2_1_Ele_in5111" relation="Edge_135"/>
    <link port="PE_2_1.Ele_in5111" relation="Edge_135"/>
    <relation cost="1" name="Edge_136"/>
    <link port="PE_2_1_Ele_in1121" relation="Edge_136"/>
    <link port="PE_2_1.Ele_in1121" relation="Edge_136"/>
    <relation cost="2" name="Edge_137"/>
    <link port="PE_2_1_Ele_in2121" relation="Edge_137"/>
    <link port="PE_2_1.Ele_in2121" relation="Edge_137"/>
    <relation cost="2" name="Edge_138"/>
    <link port="PE_2_1_Ele_in3121" relation="Edge_138"/>
    <link port="PE_2_1.Ele_in3121" relation="Edge_138"/>
    <relation cost="2" name="Edge_139"/>
    <link port="PE_2_1_Ele_in4121" relation="Edge_139"/>
    <link port="PE_2_1.Ele_in4121" relation="Edge_139"/>
    <relation cost="2" name="Edge_140"/>
    <link port="PE_2_1_Ele_in5121" relation="Edge_140"/>
    <link port="PE_2_1.Ele_in5121" relation="Edge_140"/>
    <relation cost="1" name="Edge_141"/>
    <link port="PE_2_1_Ele_in1131" relation="Edge_141"/>
    <link port="PE_2_1.Ele_in1131" relation="Edge_141"/>
    <relation cost="2" name="Edge_142"/>
    <link port="PE_2_1_Ele_in2131" relation="Edge_142"/>
    <link port="PE_2_1.Ele_in2131" relation="Edge_142"/>
    <relation cost="2" name="Edge_143"/>
    <link port="PE_2_1_Ele_in3131" relation="Edge_143"/>
    <link port="PE_2_1.Ele_in3131" relation="Edge_143"/>
    <relation cost="2" name="Edge_144"/>
    <link port="PE_2_1_Ele_in4131" relation="Edge_144"/>
    <link port="PE_2_1.Ele_in4131" relation="Edge_144"/>
    <relation cost="2" name="Edge_145"/>
    <link port="PE_2_1_Ele_in5131" relation="Edge_145"/>
    <link port="PE_2_1.Ele_in5131" relation="Edge_145"/>
    <relation cost="1" name="Edge_146"/>
    <link port="PE_2_1_Ele_in1141" relation="Edge_146"/>
    <link port="PE_2_1.Ele_in1141" relation="Edge_146"/>
    <relation cost="2" name="Edge_147"/>
    <link port="PE_2_1_Ele_in2141" relation="Edge_147"/>
    <link port="PE_2_1.Ele_in2141" relation="Edge_147"/>
    <relation cost="2" name="Edge_148"/>
    <link port="PE_2_1_Ele_in3141" relation="Edge_148"/>
    <link port="PE_2_1.Ele_in3141" relation="Edge_148"/>
    <relation cost="2" name="Edge_149"/>
    <link port="PE_2_1_Ele_in4141" relation="Edge_149"/>
    <link port="PE_2_1.Ele_in4141" relation="Edge_149"/>
    <relation cost="2" name="Edge_150"/>
    <link port="PE_2_1_Ele_in5141" relation="Edge_150"/>
    <link port="PE_2_1.Ele_in5141" relation="Edge_150"/>
    <relation cost="1" name="Edge_151"/>
    <link port="PE_2_1_Ele_in1151" relation="Edge_151"/>
    <link port="PE_2_1.Ele_in1151" relation="Edge_151"/>
    <relation cost="2" name="Edge_152"/>
    <link port="PE_2_1_Ele_in2151" relation="Edge_152"/>
    <link port="PE_2_1.Ele_in2151" relation="Edge_152"/>
    <relation cost="2" name="Edge_153"/>
    <link port="PE_2_1_Ele_in3151" relation="Edge_153"/>
    <link port="PE_2_1.Ele_in3151" relation="Edge_153"/>
    <relation cost="2" name="Edge_154"/>
    <link port="PE_2_1_Ele_in4151" relation="Edge_154"/>
    <link port="PE_2_1.Ele_in4151" relation="Edge_154"/>
    <relation cost="2" name="Edge_155"/>
    <link port="PE_2_1_Ele_in5151" relation="Edge_155"/>
    <link port="PE_2_1.Ele_in5151" relation="Edge_155"/>
    <relation cost="1" name="Edge_156"/>
    <link port="PE_2_1_Ele_in1161" relation="Edge_156"/>
    <link port="PE_2_1.Ele_in1161" relation="Edge_156"/>
    <relation cost="2" name="Edge_157"/>
    <link port="PE_2_1_Ele_in2161" relation="Edge_157"/>
    <link port="PE_2_1.Ele_in2161" relation="Edge_157"/>
    <relation cost="2" name="Edge_158"/>
    <link port="PE_2_1_Ele_in3161" relation="Edge_158"/>
    <link port="PE_2_1.Ele_in3161" relation="Edge_158"/>
    <relation cost="2" name="Edge_159"/>
    <link port="PE_2_1_Ele_in4161" relation="Edge_159"/>
    <link port="PE_2_1.Ele_in4161" relation="Edge_159"/>
    <relation cost="2" name="Edge_160"/>
    <link port="PE_2_1_Ele_in5161" relation="Edge_160"/>
    <link port="PE_2_1.Ele_in5161" relation="Edge_160"/>
    <relation cost="8" name="Edge_161"/>
    <link port="PE_2_1_Ele_out1" relation="Edge_161"/>
    <link port="PE_2_1.Ele_out1" relation="Edge_161"/>
    <relation cost="8" name="Edge_162"/>
    <link port="PE_2_1_Ele_out12" relation="Edge_162"/>
    <link port="PE_2_1.Ele_out12" relation="Edge_162"/>
  </constructure>
  <interface>
    <port name="PE_2_1_Ele_in1">
      <property name="assemblyfactor_p" value="1"/>
      <property name="tokenrate" value="1"/>
      <property name="direction" value="in"/>
      <property name="mathtype" value="real"/>
      <property name="datatype" value="float"/>
      <property name="tokentype" value="vector">
        <property name="size" value="1"/>
      </property>
      <property name="traffictype" value="stream"/>
    </port>
    <port name="PE_2_1_Ele_in2">
      <property name="assemblyfactor_p" value="1"/>
      <property name="tokenrate" value="1"/>
      <property name="direction" value="in"/>
      <property name="mathtype" value="complex"/>
      <property name="datatype" value="float"/>
      <property name="tokentype" value="scalar"/>
      <property name="traffictype" value="stream"/>
    </port>
    <port name="PE_2_1_Ele_in3">
      <property name="assemblyfactor_p" value="1"/>
      <property name="tokenrate" value="1"/>
      <property name="direction" value="in"/>
      <property name="mathtype" value="complex"/>
      <property name="datatype" value="float"/>
      <property name="tokentype" value="scalar"/>
      <property name="traffictype" value="stream"/>
    </port>
    <port name="PE_2_1_Ele_in4">
      <property name="assemblyfactor_p" value="1"/>
      <property name="tokenrate" value="1"/>
      <property name="direction" value="in"/>
      <property name="mathtype" value="complex"/>
      <property name="datatype" value="float"/>
      <property name="tokentype" value="scalar"/>
      <property name="traffictype" value="stream"/>
    </port>
    <port name="PE_2_1_Ele_in5">
      <property name="assemblyfactor_p" value="1"/>
      <property name="tokenrate" value="1"/>
      <property name="direction" value="in"/>
      <property name="mathtype" value="complex"/>
      <property name="datatype" value="float"/>
      <property name="tokentype" value="scalar"/>
      <property name="traffictype" value="stream"/>
    </port>
    <port name="PE_2_1_Ele_in12">
      <property name="assemblyfactor_p" value="1"/>
      <property name="tokenrate" value="1"/>
      <property name="direction" value="in"/>
      <property name="mathtype" value="real"/>
      <property name="datatype" value="float"/>
      <property name="tokentype" value="vector">
        <property name="size" value="1"/>
      </property>
      <property name="traffictype" value="stream"/>
    </port>
    <port name="PE_2_1_Ele_in22">
      <property name="assemblyfactor_p" value="1"/>
      <property name="tokenrate" value="1"/>
      <property name="direction" value="in"/>
      <property name="mathtype" value="complex"/>
      <property name="datatype" value="float"/>
      <property name="tokentype" value="scalar"/>
      <property name="traffictype" value="stream"/>
    </port>
    <port name="PE_2_1_Ele_in32">
      <property name="assemblyfactor_p" value="1"/>
      <property name="tokenrate" value="1"/>
      <property name="direction" value="in"/>
      <property name="mathtype" value="complex"/>
      <property name="datatype" value="float"/>
      <property name="tokentype" value="scalar"/>
      <property name="traffictype" value="stream"/>
    </port>
    <port name="PE_2_1_Ele_in42">
      <property name="assemblyfactor_p" value="1"/>
      <property name="tokenrate" value="1"/>
      <property name="direction" value="in"/>
      <property name="mathtype" value="complex"/>
      <property name="datatype" value="float"/>
      <property name="tokentype" value="scalar"/>
      <property name="traffictype" value="stream"/>
    </port>
    <port name="PE_2_1_Ele_in52">
      <property name="assemblyfactor_p" value="1"/>
      <property name="tokenrate" value="1"/>
      <property name="direction" value="in"/>
      <property name="mathtype" value="complex"/>
      <property name="datatype" value="float"/>
      <property name="tokentype" value="scalar"/>
      <property name="traffictype" value="stream"/>
    </port>
    <port name="PE_2_1_Ele_in13">
      <property name="assemblyfactor_p" value="1"/>
      <property name="tokenrate" value="1"/>
      <property name="direction" value="in"/>
      <property name="mathtype" value="real"/>
      <property name="datatype" value="float"/>
      <property name="tokentype" value="vector">
        <property name="size" value="1"/>
      </property>
      <property name="traffictype" value="stream"/>
    </port>
    <port name="PE_2_1_Ele_in23">
      <property name="assemblyfactor_p" value="1"/>
      <property name="tokenrate" value="1"/>
      <property name="direction" value="in"/>
      <property name="mathtype" value="complex"/>
      <property name="datatype" value="float"/>
      <property name="tokentype" value="scalar"/>
      <property name="traffictype" value="stream"/>
    </port>
    <port name="PE_2_1_Ele_in33">
      <property name="assemblyfactor_p" value="1"/>
      <property name="tokenrate" value="1"/>
      <property name="direction" value="in"/>
      <property name="mathtype" value="complex"/>
      <property name="datatype" value="float"/>
      <property name="tokentype" value="scalar"/>
      <property name="traffictype" value="stream"/>
    </port>
    <port name="PE_2_1_Ele_in43">
      <property name="assemblyfactor_p" value="1"/>
      <property name="tokenrate" value="1"/>
      <property name="direction" value="in"/>
      <property name="mathtype" value="complex"/>
      <property name="datatype" value="float"/>
      <property name="tokentype" value="scalar"/>
      <property name="traffictype" value="stream"/>
    </port>
    <port name="PE_2_1_Ele_in53">
      <property name="assemblyfactor_p" value="1"/>
      <property name="tokenrate" value="1"/>
      <property name="direction" value="in"/>
      <property name="mathtype" value="complex"/>
      <property name="datatype" value="float"/>
      <property name="tokentype" value="scalar"/>
      <property name="traffictype" value="stream"/>
    </port>
    <port name="PE_2_1_Ele_in14">
      <property name="assemblyfactor_p" value="1"/>
      <property name="tokenrate" value="1"/>
      <property name="direction" value="in"/>
      <property name="mathtype" value="real"/>
      <property name="datatype" value="float"/>
      <property name="tokentype" value="vector">
        <property name="size" value="1"/>
      </property>
      <property name="traffictype" value="stream"/>
    </port>
    <port name="PE_2_1_Ele_in24">
      <property name="assemblyfactor_p" value="1"/>
      <property name="tokenrate" value="1"/>
      <property name="direction" value="in"/>
      <property name="mathtype" value="complex"/>
      <property name="datatype" value="float"/>
      <property name="tokentype" value="scalar"/>
      <property name="traffictype" value="stream"/>
    </port>
    <port name="PE_2_1_Ele_in34">
      <property name="assemblyfactor_p" value="1"/>
      <property name="tokenrate" value="1"/>
      <property name="direction" value="in"/>
      <property name="mathtype" value="complex"/>
      <property name="datatype" value="float"/>
      <property name="tokentype" value="scalar"/>
      <property name="traffictype" value="stream"/>
    </port>
    <port name="PE_2_1_Ele_in44">
      <property name="assemblyfactor_p" value="1"/>
      <property name="tokenrate" value="1"/>
      <property name="direction" value="in"/>
      <property name="mathtype" value="complex"/>
      <property name="datatype" value="float"/>
      <property name="tokentype" value="scalar"/>
      <property name="traffictype" value="stream"/>
    </port>
    <port name="PE_2_1_Ele_in54">
      <property name="assemblyfactor_p" value="1"/>
      <property name="tokenrate" value="1"/>
      <property name="direction" value="in"/>
      <property name="mathtype" value="complex"/>
      <property name="datatype" value="float"/>
      <property name="tokentype" value="scalar"/>
      <property name="traffictype" value="stream"/>
    </port>
    <port name="PE_2_1_Ele_in15">
      <property name="assemblyfactor_p" value="1"/>
      <property name="tokenrate" value="1"/>
      <property name="direction" value="in"/>
      <property name="mathtype" value="real"/>
      <property name="datatype" value="float"/>
      <property name="tokentype" value="vector">
        <property name="size" value="1"/>
      </property>
      <property name="traffictype" value="stream"/>
    </port>
    <port name="PE_2_1_Ele_in25">
      <property name="assemblyfactor_p" value="1"/>
      <property name="tokenrate" value="1"/>
      <property name="direction" value="in"/>
      <property name="mathtype" value="complex"/>
      <property name="datatype" value="float"/>
      <property name="tokentype" value="scalar"/>
      <property name="traffictype" value="stream"/>
    </port>
    <port name="PE_2_1_Ele_in35">
      <property name="assemblyfactor_p" value="1"/>
      <property name="tokenrate" value="1"/>
      <property name="direction" value="in"/>
      <property name="mathtype" value="complex"/>
      <property name="datatype" value="float"/>
      <property name="tokentype" value="scalar"/>
      <property name="traffictype" value="stream"/>
    </port>
    <port name="PE_2_1_Ele_in45">
      <property name="assemblyfactor_p" value="1"/>
      <property name="tokenrate" value="1"/>
      <property name="direction" value="in"/>
      <property name="mathtype" value="complex"/>
      <property name="datatype" value="float"/>
      <property name="tokentype" value="scalar"/>
      <property name="traffictype" value="stream"/>
    </port>
    <port name="PE_2_1_Ele_in55">
      <property name="assemblyfactor_p" value="1"/>
      <property name="tokenrate" value="1"/>
      <property name="direction" value="in"/>
      <property name="mathtype" value="complex"/>
      <property name="datatype" value="float"/>
      <property name="tokentype" value="scalar"/>
      <property name="traffictype" value="stream"/>
    </port>
    <port name="PE_2_1_Ele_in16">
      <property name="assemblyfactor_p" value="1"/>
      <property name="tokenrate" value="1"/>
      <property name="direction" value="in"/>
      <property name="mathtype" value="real"/>
      <property name="datatype" value="float"/>
      <property name="tokentype" value="vector">
        <property name="size" value="1"/>
      </property>
      <property name="traffictype" value="stream"/>
    </port>
    <port name="PE_2_1_Ele_in26">
      <property name="assemblyfactor_p" value="1"/>
      <property name="tokenrate" value="1"/>
      <property name="direction" value="in"/>
      <property name="mathtype" value="complex"/>
      <property name="datatype" value="float"/>
      <property name="tokentype" value="scalar"/>
      <property name="traffictype" value="stream"/>
    </port>
    <port name="PE_2_1_Ele_in36">
      <property name="assemblyfactor_p" value="1"/>
      <property name="tokenrate" value="1"/>
      <property name="direction" value="in"/>
      <property name="mathtype" value="complex"/>
      <property name="datatype" value="float"/>
      <property name="tokentype" value="scalar"/>
      <property name="traffictype" value="stream"/>
    </port>
    <port name="PE_2_1_Ele_in46">
      <property name="assemblyfactor_p" value="1"/>
      <property name="tokenrate" value="1"/>
      <property name="direction" value="in"/>
      <property name="mathtype" value="complex"/>
      <property name="datatype" value="float"/>
      <property name="tokentype" value="scalar"/>
      <property name="traffictype" value="stream"/>
    </port>
    <port name="PE_2_1_Ele_in56">
      <property name="assemblyfactor_p" value="1"/>
      <property name="tokenrate" value="1"/>
      <property name="direction" value="in"/>
      <property name="mathtype" value="complex"/>
      <property name="datatype" value="float"/>
      <property name="tokentype" value="scalar"/>
      <property name="traffictype" value="stream"/>
    </port>
    <port name="PE_2_1_Ele_in17">
      <property name="assemblyfactor_p" value="1"/>
      <property name="tokenrate" value="1"/>
      <property name="direction" value="in"/>
      <property name="mathtype" value="real"/>
      <property name="datatype" value="float"/>
      <property name="tokentype" value="vector">
        <property name="size" value="1"/>
      </property>
      <property name="traffictype" value="stream"/>
    </port>
    <port name="PE_2_1_Ele_in27">
      <property name="assemblyfactor_p" value="1"/>
      <property name="tokenrate" value="1"/>
      <property name="direction" value="in"/>
      <property name="mathtype" value="complex"/>
      <property name="datatype" value="float"/>
      <property name="tokentype" value="scalar"/>
      <property name="traffictype" value="stream"/>
    </port>
    <port name="PE_2_1_Ele_in37">
      <property name="assemblyfactor_p" value="1"/>
      <property name="tokenrate" value="1"/>
      <property name="direction" value="in"/>
      <property name="mathtype" value="complex"/>
      <property name="datatype" value="float"/>
      <property name="tokentype" value="scalar"/>
      <property name="traffictype" value="stream"/>
    </port>
    <port name="PE_2_1_Ele_in47">
      <property name="assemblyfactor_p" value="1"/>
      <property name="tokenrate" value="1"/>
      <property name="direction" value="in"/>
      <property name="mathtype" value="complex"/>
      <property name="datatype" value="float"/>
      <property name="tokentype" value="scalar"/>
      <property name="traffictype" value="stream"/>
    </port>
    <port name="PE_2_1_Ele_in57">
      <property name="assemblyfactor_p" value="1"/>
      <property name="tokenrate" value="1"/>
      <property name="direction" value="in"/>
      <property name="mathtype" value="complex"/>
      <property name="datatype" value="float"/>
      <property name="tokentype" value="scalar"/>
      <property name="traffictype" value="stream"/>
    </port>
    <port name="PE_2_1_Ele_in18">
      <property name="assemblyfactor_p" value="1"/>
      <property name="tokenrate" value="1"/>
      <property name="direction" value="in"/>
      <property name="mathtype" value="real"/>
      <property name="datatype" value="float"/>
      <property name="tokentype" value="vector">
        <property name="size" value="1"/>
      </property>
      <property name="traffictype" value="stream"/>
    </port>
    <port name="PE_2_1_Ele_in28">
      <property name="assemblyfactor_p" value="1"/>
      <property name="tokenrate" value="1"/>
      <property name="direction" value="in"/>
      <property name="mathtype" value="complex"/>
      <property name="datatype" value="float"/>
      <property name="tokentype" value="scalar"/>
      <property name="traffictype" value="stream"/>
    </port>
    <port name="PE_2_1_Ele_in38">
      <property name="assemblyfactor_p" value="1"/>
      <property name="tokenrate" value="1"/>
      <property name="direction" value="in"/>
      <property name="mathtype" value="complex"/>
      <property name="datatype" value="float"/>
      <property name="tokentype" value="scalar"/>
      <property name="traffictype" value="stream"/>
    </port>
    <port name="PE_2_1_Ele_in48">
      <property name="assemblyfactor_p" value="1"/>
      <property name="tokenrate" value="1"/>
      <property name="direction" value="in"/>
      <property name="mathtype" value="complex"/>
      <property name="datatype" value="float"/>
      <property name="tokentype" value="scalar"/>
      <property name="traffictype" value="stream"/>
    </port>
    <port name="PE_2_1_Ele_in58">
      <property name="assemblyfactor_p" value="1"/>
      <property name="tokenrate" value="1"/>
      <property name="direction" value="in"/>
      <property name="mathtype" value="complex"/>
      <property name="datatype" value="float"/>
      <property name="tokentype" value="scalar"/>
      <property name="traffictype" value="stream"/>
    </port>
    <port name="PE_2_1_Ele_in19">
      <property name="assemblyfactor_p" value="1"/>
      <property name="tokenrate" value="1"/>
      <property name="direction" value="in"/>
      <property name="mathtype" value="real"/>
      <property name="datatype" value="float"/>
      <property name="tokentype" value="vector">
        <property name="size" value="1"/>
      </property>
      <property name="traffictype" value="stream"/>
    </port>
    <port name="PE_2_1_Ele_in29">
      <property name="assemblyfactor_p" value="1"/>
      <property name="tokenrate" value="1"/>
      <property name="direction" value="in"/>
      <property name="mathtype" value="complex"/>
      <property name="datatype" value="float"/>
      <property name="tokentype" value="scalar"/>
      <property name="traffictype" value="stream"/>
    </port>
    <port name="PE_2_1_Ele_in39">
      <property name="assemblyfactor_p" value="1"/>
      <property name="tokenrate" value="1"/>
      <property name="direction" value="in"/>
      <property name="mathtype" value="complex"/>
      <property name="datatype" value="float"/>
      <property name="tokentype" value="scalar"/>
      <property name="traffictype" value="stream"/>
    </port>
    <port name="PE_2_1_Ele_in49">
      <property name="assemblyfactor_p" value="1"/>
      <property name="tokenrate" value="1"/>
      <property name="direction" value="in"/>
      <property name="mathtype" value="complex"/>
      <property name="datatype" value="float"/>
      <property name="tokentype" value="scalar"/>
      <property name="traffictype" value="stream"/>
    </port>
    <port name="PE_2_1_Ele_in59">
      <property name="assemblyfactor_p" value="1"/>
      <property name="tokenrate" value="1"/>
      <property name="direction" value="in"/>
      <property name="mathtype" value="complex"/>
      <property name="datatype" value="float"/>
      <property name="tokentype" value="scalar"/>
      <property name="traffictype" value="stream"/>
    </port>
    <port name="PE_2_1_Ele_in110">
      <property name="assemblyfactor_p" value="1"/>
      <property name="tokenrate" value="1"/>
      <property name="direction" value="in"/>
      <property name="mathtype" value="real"/>
      <property name="datatype" value="float"/>
      <property name="tokentype" value="vector">
        <property name="size" value="1"/>
      </property>
      <property name="traffictype" value="stream"/>
    </port>
    <port name="PE_2_1_Ele_in210">
      <property name="assemblyfactor_p" value="1"/>
      <property name="tokenrate" value="1"/>
      <property name="direction" value="in"/>
      <property name="mathtype" value="complex"/>
      <property name="datatype" value="float"/>
      <property name="tokentype" value="scalar"/>
      <property name="traffictype" value="stream"/>
    </port>
    <port name="PE_2_1_Ele_in310">
      <property name="assemblyfactor_p" value="1"/>
      <property name="tokenrate" value="1"/>
      <property name="direction" value="in"/>
      <property name="mathtype" value="complex"/>
      <property name="datatype" value="float"/>
      <property name="tokentype" value="scalar"/>
      <property name="traffictype" value="stream"/>
    </port>
    <port name="PE_2_1_Ele_in410">
      <property name="assemblyfactor_p" value="1"/>
      <property name="tokenrate" value="1"/>
      <property name="direction" value="in"/>
      <property name="mathtype" value="complex"/>
      <property name="datatype" value="float"/>
      <property name="tokentype" value="scalar"/>
      <property name="traffictype" value="stream"/>
    </port>
    <port name="PE_2_1_Ele_in510">
      <property name="assemblyfactor_p" value="1"/>
      <property name="tokenrate" value="1"/>
      <property name="direction" value="in"/>
      <property name="mathtype" value="complex"/>
      <property name="datatype" value="float"/>
      <property name="tokentype" value="scalar"/>
      <property name="traffictype" value="stream"/>
    </port>
    <port name="PE_2_1_Ele_in111">
      <property name="assemblyfactor_p" value="1"/>
      <property name="tokenrate" value="1"/>
      <property name="direction" value="in"/>
      <property name="mathtype" value="real"/>
      <property name="datatype" value="float"/>
      <property name="tokentype" value="vector">
        <property name="size" value="1"/>
      </property>
      <property name="traffictype" value="stream"/>
    </port>
    <port name="PE_2_1_Ele_in211">
      <property name="assemblyfactor_p" value="1"/>
      <property name="tokenrate" value="1"/>
      <property name="direction" value="in"/>
      <property name="mathtype" value="complex"/>
      <property name="datatype" value="float"/>
      <property name="tokentype" value="scalar"/>
      <property name="traffictype" value="stream"/>
    </port>
    <port name="PE_2_1_Ele_in311">
      <property name="assemblyfactor_p" value="1"/>
      <property name="tokenrate" value="1"/>
      <property name="direction" value="in"/>
      <property name="mathtype" value="complex"/>
      <property name="datatype" value="float"/>
      <property name="tokentype" value="scalar"/>
      <property name="traffictype" value="stream"/>
    </port>
    <port name="PE_2_1_Ele_in411">
      <property name="assemblyfactor_p" value="1"/>
      <property name="tokenrate" value="1"/>
      <property name="direction" value="in"/>
      <property name="mathtype" value="complex"/>
      <property name="datatype" value="float"/>
      <property name="tokentype" value="scalar"/>
      <property name="traffictype" value="stream"/>
    </port>
    <port name="PE_2_1_Ele_in511">
      <property name="assemblyfactor_p" value="1"/>
      <property name="tokenrate" value="1"/>
      <property name="direction" value="in"/>
      <property name="mathtype" value="complex"/>
      <property name="datatype" value="float"/>
      <property name="tokentype" value="scalar"/>
      <property name="traffictype" value="stream"/>
    </port>
    <port name="PE_2_1_Ele_in112">
      <property name="assemblyfactor_p" value="1"/>
      <property name="tokenrate" value="1"/>
      <property name="direction" value="in"/>
      <property name="mathtype" value="real"/>
      <property name="datatype" value="float"/>
      <property name="tokentype" value="vector">
        <property name="size" value="1"/>
      </property>
      <property name="traffictype" value="stream"/>
    </port>
    <port name="PE_2_1_Ele_in212">
      <property name="assemblyfactor_p" value="1"/>
      <property name="tokenrate" value="1"/>
      <property name="direction" value="in"/>
      <property name="mathtype" value="complex"/>
      <property name="datatype" value="float"/>
      <property name="tokentype" value="scalar"/>
      <property name="traffictype" value="stream"/>
    </port>
    <port name="PE_2_1_Ele_in312">
      <property name="assemblyfactor_p" value="1"/>
      <property name="tokenrate" value="1"/>
      <property name="direction" value="in"/>
      <property name="mathtype" value="complex"/>
      <property name="datatype" value="float"/>
      <property name="tokentype" value="scalar"/>
      <property name="traffictype" value="stream"/>
    </port>
    <port name="PE_2_1_Ele_in412">
      <property name="assemblyfactor_p" value="1"/>
      <property name="tokenrate" value="1"/>
      <property name="direction" value="in"/>
      <property name="mathtype" value="complex"/>
      <property name="datatype" value="float"/>
      <property name="tokentype" value="scalar"/>
      <property name="traffictype" value="stream"/>
    </port>
    <port name="PE_2_1_Ele_in512">
      <property name="assemblyfactor_p" value="1"/>
      <property name="tokenrate" value="1"/>
      <property name="direction" value="in"/>
      <property name="mathtype" value="complex"/>
      <property name="datatype" value="float"/>
      <property name="tokentype" value="scalar"/>
      <property name="traffictype" value="stream"/>
    </port>
    <port name="PE_2_1_Ele_in113">
      <property name="assemblyfactor_p" value="1"/>
      <property name="tokenrate" value="1"/>
      <property name="direction" value="in"/>
      <property name="mathtype" value="real"/>
      <property name="datatype" value="float"/>
      <property name="tokentype" value="vector">
        <property name="size" value="1"/>
      </property>
      <property name="traffictype" value="stream"/>
    </port>
    <port name="PE_2_1_Ele_in213">
      <property name="assemblyfactor_p" value="1"/>
      <property name="tokenrate" value="1"/>
      <property name="direction" value="in"/>
      <property name="mathtype" value="complex"/>
      <property name="datatype" value="float"/>
      <property name="tokentype" value="scalar"/>
      <property name="traffictype" value="stream"/>
    </port>
    <port name="PE_2_1_Ele_in313">
      <property name="assemblyfactor_p" value="1"/>
      <property name="tokenrate" value="1"/>
      <property name="direction" value="in"/>
      <property name="mathtype" value="complex"/>
      <property name="datatype" value="float"/>
      <property name="tokentype" value="scalar"/>
      <property name="traffictype" value="stream"/>
    </port>
    <port name="PE_2_1_Ele_in413">
      <property name="assemblyfactor_p" value="1"/>
      <property name="tokenrate" value="1"/>
      <property name="direction" value="in"/>
      <property name="mathtype" value="complex"/>
      <property name="datatype" value="float"/>
      <property name="tokentype" value="scalar"/>
      <property name="traffictype" value="stream"/>
    </port>
    <port name="PE_2_1_Ele_in513">
      <property name="assemblyfactor_p" value="1"/>
      <property name="tokenrate" value="1"/>
      <property name="direction" value="in"/>
      <property name="mathtype" value="complex"/>
      <property name="datatype" value="float"/>
      <property name="tokentype" value="scalar"/>
      <property name="traffictype" value="stream"/>
    </port>
    <port name="PE_2_1_Ele_in114">
      <property name="assemblyfactor_p" value="1"/>
      <property name="tokenrate" value="1"/>
      <property name="direction" value="in"/>
      <property name="mathtype" value="real"/>
      <property name="datatype" value="float"/>
      <property name="tokentype" value="vector">
        <property name="size" value="1"/>
      </property>
      <property name="traffictype" value="stream"/>
    </port>
    <port name="PE_2_1_Ele_in214">
      <property name="assemblyfactor_p" value="1"/>
      <property name="tokenrate" value="1"/>
      <property name="direction" value="in"/>
      <property name="mathtype" value="complex"/>
      <property name="datatype" value="float"/>
      <property name="tokentype" value="scalar"/>
      <property name="traffictype" value="stream"/>
    </port>
    <port name="PE_2_1_Ele_in314">
      <property name="assemblyfactor_p" value="1"/>
      <property name="tokenrate" value="1"/>
      <property name="direction" value="in"/>
      <property name="mathtype" value="complex"/>
      <property name="datatype" value="float"/>
      <property name="tokentype" value="scalar"/>
      <property name="traffictype" value="stream"/>
    </port>
    <port name="PE_2_1_Ele_in414">
      <property name="assemblyfactor_p" value="1"/>
      <property name="tokenrate" value="1"/>
      <property name="direction" value="in"/>
      <property name="mathtype" value="complex"/>
      <property name="datatype" value="float"/>
      <property name="tokentype" value="scalar"/>
      <property name="traffictype" value="stream"/>
    </port>
    <port name="PE_2_1_Ele_in514">
      <property name="assemblyfactor_p" value="1"/>
      <property name="tokenrate" value="1"/>
      <property name="direction" value="in"/>
      <property name="mathtype" value="complex"/>
      <property name="datatype" value="float"/>
      <property name="tokentype" value="scalar"/>
      <property name="traffictype" value="stream"/>
    </port>
    <port name="PE_2_1_Ele_in115">
      <property name="assemblyfactor_p" value="1"/>
      <property name="tokenrate" value="1"/>
      <property name="direction" value="in"/>
      <property name="mathtype" value="real"/>
      <property name="datatype" value="float"/>
      <property name="tokentype" value="vector">
        <property name="size" value="1"/>
      </property>
      <property name="traffictype" value="stream"/>
    </port>
    <port name="PE_2_1_Ele_in215">
      <property name="assemblyfactor_p" value="1"/>
      <property name="tokenrate" value="1"/>
      <property name="direction" value="in"/>
      <property name="mathtype" value="complex"/>
      <property name="datatype" value="float"/>
      <property name="tokentype" value="scalar"/>
      <property name="traffictype" value="stream"/>
    </port>
    <port name="PE_2_1_Ele_in315">
      <property name="assemblyfactor_p" value="1"/>
      <property name="tokenrate" value="1"/>
      <property name="direction" value="in"/>
      <property name="mathtype" value="complex"/>
      <property name="datatype" value="float"/>
      <property name="tokentype" value="scalar"/>
      <property name="traffictype" value="stream"/>
    </port>
    <port name="PE_2_1_Ele_in415">
      <property name="assemblyfactor_p" value="1"/>
      <property name="tokenrate" value="1"/>
      <property name="direction" value="in"/>
      <property name="mathtype" value="complex"/>
      <property name="datatype" value="float"/>
      <property name="tokentype" value="scalar"/>
      <property name="traffictype" value="stream"/>
    </port>
    <port name="PE_2_1_Ele_in515">
      <property name="assemblyfactor_p" value="1"/>
      <property name="tokenrate" value="1"/>
      <property name="direction" value="in"/>
      <property name="mathtype" value="complex"/>
      <property name="datatype" value="float"/>
      <property name="tokentype" value="scalar"/>
      <property name="traffictype" value="stream"/>
    </port>
    <port name="PE_2_1_Ele_in116">
      <property name="assemblyfactor_p" value="1"/>
      <property name="tokenrate" value="1"/>
      <property name="direction" value="in"/>
      <property name="mathtype" value="real"/>
      <property name="datatype" value="float"/>
      <property name="tokentype" value="vector">
        <property name="size" value="1"/>
      </property>
      <property name="traffictype" value="stream"/>
    </port>
    <port name="PE_2_1_Ele_in216">
      <property name="assemblyfactor_p" value="1"/>
      <property name="tokenrate" value="1"/>
      <property name="direction" value="in"/>
      <property name="mathtype" value="complex"/>
      <property name="datatype" value="float"/>
      <property name="tokentype" value="scalar"/>
      <property name="traffictype" value="stream"/>
    </port>
    <port name="PE_2_1_Ele_in316">
      <property name="assemblyfactor_p" value="1"/>
      <property name="tokenrate" value="1"/>
      <property name="direction" value="in"/>
      <property name="mathtype" value="complex"/>
      <property name="datatype" value="float"/>
      <property name="tokentype" value="scalar"/>
      <property name="traffictype" value="stream"/>
    </port>
    <port name="PE_2_1_Ele_in416">
      <property name="assemblyfactor_p" value="1"/>
      <property name="tokenrate" value="1"/>
      <property name="direction" value="in"/>
      <property name="mathtype" value="complex"/>
      <property name="datatype" value="float"/>
      <property name="tokentype" value="scalar"/>
      <property name="traffictype" value="stream"/>
    </port>
    <port name="PE_2_1_Ele_in516">
      <property name="assemblyfactor_p" value="1"/>
      <property name="tokenrate" value="1"/>
      <property name="direction" value="in"/>
      <property name="mathtype" value="complex"/>
      <property name="datatype" value="float"/>
      <property name="tokentype" value="scalar"/>
      <property name="traffictype" value="stream"/>
    </port>
    <port name="PE_2_1_Ele_in11">
      <property name="assemblyfactor_p" value="1"/>
      <property name="tokenrate" value="1"/>
      <property name="direction" value="in"/>
      <property name="mathtype" value="real"/>
      <property name="datatype" value="float"/>
      <property name="tokentype" value="vector">
        <property name="size" value="1"/>
      </property>
      <property name="traffictype" value="stream"/>
    </port>
    <port name="PE_2_1_Ele_in21">
      <property name="assemblyfactor_p" value="1"/>
      <property name="tokenrate" value="1"/>
      <property name="direction" value="in"/>
      <property name="mathtype" value="complex"/>
      <property name="datatype" value="float"/>
      <property name="tokentype" value="scalar"/>
      <property name="traffictype" value="stream"/>
    </port>
    <port name="PE_2_1_Ele_in31">
      <property name="assemblyfactor_p" value="1"/>
      <property name="tokenrate" value="1"/>
      <property name="direction" value="in"/>
      <property name="mathtype" value="complex"/>
      <property name="datatype" value="float"/>
      <property name="tokentype" value="scalar"/>
      <property name="traffictype" value="stream"/>
    </port>
    <port name="PE_2_1_Ele_in41">
      <property name="assemblyfactor_p" value="1"/>
      <property name="tokenrate" value="1"/>
      <property name="direction" value="in"/>
      <property name="mathtype" value="complex"/>
      <property name="datatype" value="float"/>
      <property name="tokentype" value="scalar"/>
      <property name="traffictype" value="stream"/>
    </port>
    <port name="PE_2_1_Ele_in51">
      <property name="assemblyfactor_p" value="1"/>
      <property name="tokenrate" value="1"/>
      <property name="direction" value="in"/>
      <property name="mathtype" value="complex"/>
      <property name="datatype" value="float"/>
      <property name="tokentype" value="scalar"/>
      <property name="traffictype" value="stream"/>
    </port>
    <port name="PE_2_1_Ele_in121">
      <property name="assemblyfactor_p" value="1"/>
      <property name="tokenrate" value="1"/>
      <property name="direction" value="in"/>
      <property name="mathtype" value="real"/>
      <property name="datatype" value="float"/>
      <property name="tokentype" value="vector">
        <property name="size" value="1"/>
      </property>
      <property name="traffictype" value="stream"/>
    </port>
    <port name="PE_2_1_Ele_in221">
      <property name="assemblyfactor_p" value="1"/>
      <property name="tokenrate" value="1"/>
      <property name="direction" value="in"/>
      <property name="mathtype" value="complex"/>
      <property name="datatype" value="float"/>
      <property name="tokentype" value="scalar"/>
      <property name="traffictype" value="stream"/>
    </port>
    <port name="PE_2_1_Ele_in321">
      <property name="assemblyfactor_p" value="1"/>
      <property name="tokenrate" value="1"/>
      <property name="direction" value="in"/>
      <property name="mathtype" value="complex"/>
      <property name="datatype" value="float"/>
      <property name="tokentype" value="scalar"/>
      <property name="traffictype" value="stream"/>
    </port>
    <port name="PE_2_1_Ele_in421">
      <property name="assemblyfactor_p" value="1"/>
      <property name="tokenrate" value="1"/>
      <property name="direction" value="in"/>
      <property name="mathtype" value="complex"/>
      <property name="datatype" value="float"/>
      <property name="tokentype" value="scalar"/>
      <property name="traffictype" value="stream"/>
    </port>
    <port name="PE_2_1_Ele_in521">
      <property name="assemblyfactor_p" value="1"/>
      <property name="tokenrate" value="1"/>
      <property name="direction" value="in"/>
      <property name="mathtype" value="complex"/>
      <property name="datatype" value="float"/>
      <property name="tokentype" value="scalar"/>
      <property name="traffictype" value="stream"/>
    </port>
    <port name="PE_2_1_Ele_in131">
      <property name="assemblyfactor_p" value="1"/>
      <property name="tokenrate" value="1"/>
      <property name="direction" value="in"/>
      <property name="mathtype" value="real"/>
      <property name="datatype" value="float"/>
      <property name="tokentype" value="vector">
        <property name="size" value="1"/>
      </property>
      <property name="traffictype" value="stream"/>
    </port>
    <port name="PE_2_1_Ele_in231">
      <property name="assemblyfactor_p" value="1"/>
      <property name="tokenrate" value="1"/>
      <property name="direction" value="in"/>
      <property name="mathtype" value="complex"/>
      <property name="datatype" value="float"/>
      <property name="tokentype" value="scalar"/>
      <property name="traffictype" value="stream"/>
    </port>
    <port name="PE_2_1_Ele_in331">
      <property name="assemblyfactor_p" value="1"/>
      <property name="tokenrate" value="1"/>
      <property name="direction" value="in"/>
      <property name="mathtype" value="complex"/>
      <property name="datatype" value="float"/>
      <property name="tokentype" value="scalar"/>
      <property name="traffictype" value="stream"/>
    </port>
    <port name="PE_2_1_Ele_in431">
      <property name="assemblyfactor_p" value="1"/>
      <property name="tokenrate" value="1"/>
      <property name="direction" value="in"/>
      <property name="mathtype" value="complex"/>
      <property name="datatype" value="float"/>
      <property name="tokentype" value="scalar"/>
      <property name="traffictype" value="stream"/>
    </port>
    <port name="PE_2_1_Ele_in531">
      <property name="assemblyfactor_p" value="1"/>
      <property name="tokenrate" value="1"/>
      <property name="direction" value="in"/>
      <property name="mathtype" value="complex"/>
      <property name="datatype" value="float"/>
      <property name="tokentype" value="scalar"/>
      <property name="traffictype" value="stream"/>
    </port>
    <port name="PE_2_1_Ele_in141">
      <property name="assemblyfactor_p" value="1"/>
      <property name="tokenrate" value="1"/>
      <property name="direction" value="in"/>
      <property name="mathtype" value="real"/>
      <property name="datatype" value="float"/>
      <property name="tokentype" value="vector">
        <property name="size" value="1"/>
      </property>
      <property name="traffictype" value="stream"/>
    </port>
    <port name="PE_2_1_Ele_in241">
      <property name="assemblyfactor_p" value="1"/>
      <property name="tokenrate" value="1"/>
      <property name="direction" value="in"/>
      <property name="mathtype" value="complex"/>
      <property name="datatype" value="float"/>
      <property name="tokentype" value="scalar"/>
      <property name="traffictype" value="stream"/>
    </port>
    <port name="PE_2_1_Ele_in341">
      <property name="assemblyfactor_p" value="1"/>
      <property name="tokenrate" value="1"/>
      <property name="direction" value="in"/>
      <property name="mathtype" value="complex"/>
      <property name="datatype" value="float"/>
      <property name="tokentype" value="scalar"/>
      <property name="traffictype" value="stream"/>
    </port>
    <port name="PE_2_1_Ele_in441">
      <property name="assemblyfactor_p" value="1"/>
      <property name="tokenrate" value="1"/>
      <property name="direction" value="in"/>
      <property name="mathtype" value="complex"/>
      <property name="datatype" value="float"/>
      <property name="tokentype" value="scalar"/>
      <property name="traffictype" value="stream"/>
    </port>
    <port name="PE_2_1_Ele_in541">
      <property name="assemblyfactor_p" value="1"/>
      <property name="tokenrate" value="1"/>
      <property name="direction" value="in"/>
      <property name="mathtype" value="complex"/>
      <property name="datatype" value="float"/>
      <property name="tokentype" value="scalar"/>
      <property name="traffictype" value="stream"/>
    </port>
    <port name="PE_2_1_Ele_in151">
      <property name="assemblyfactor_p" value="1"/>
      <property name="tokenrate" value="1"/>
      <property name="direction" value="in"/>
      <property name="mathtype" value="real"/>
      <property name="datatype" value="float"/>
      <property name="tokentype" value="vector">
        <property name="size" value="1"/>
      </property>
      <property name="traffictype" value="stream"/>
    </port>
    <port name="PE_2_1_Ele_in251">
      <property name="assemblyfactor_p" value="1"/>
      <property name="tokenrate" value="1"/>
      <property name="direction" value="in"/>
      <property name="mathtype" value="complex"/>
      <property name="datatype" value="float"/>
      <property name="tokentype" value="scalar"/>
      <property name="traffictype" value="stream"/>
    </port>
    <port name="PE_2_1_Ele_in351">
      <property name="assemblyfactor_p" value="1"/>
      <property name="tokenrate" value="1"/>
      <property name="direction" value="in"/>
      <property name="mathtype" value="complex"/>
      <property name="datatype" value="float"/>
      <property name="tokentype" value="scalar"/>
      <property name="traffictype" value="stream"/>
    </port>
    <port name="PE_2_1_Ele_in451">
      <property name="assemblyfactor_p" value="1"/>
      <property name="tokenrate" value="1"/>
      <property name="direction" value="in"/>
      <property name="mathtype" value="complex"/>
      <property name="datatype" value="float"/>
      <property name="tokentype" value="scalar"/>
      <property name="traffictype" value="stream"/>
    </port>
    <port name="PE_2_1_Ele_in551">
      <property name="assemblyfactor_p" value="1"/>
      <property name="tokenrate" value="1"/>
      <property name="direction" value="in"/>
      <property name="mathtype" value="complex"/>
      <property name="datatype" value="float"/>
      <property name="tokentype" value="scalar"/>
      <property name="traffictype" value="stream"/>
    </port>
    <port name="PE_2_1_Ele_in161">
      <property name="assemblyfactor_p" value="1"/>
      <property name="tokenrate" value="1"/>
      <property name="direction" value="in"/>
      <property name="mathtype" value="real"/>
      <property name="datatype" value="float"/>
      <property name="tokentype" value="vector">
        <property name="size" value="1"/>
      </property>
      <property name="traffictype" value="stream"/>
    </port>
    <port name="PE_2_1_Ele_in261">
      <property name="assemblyfactor_p" value="1"/>
      <property name="tokenrate" value="1"/>
      <property name="direction" value="in"/>
      <property name="mathtype" value="complex"/>
      <property name="datatype" value="float"/>
      <property name="tokentype" value="scalar"/>
      <property name="traffictype" value="stream"/>
    </port>
    <port name="PE_2_1_Ele_in361">
      <property name="assemblyfactor_p" value="1"/>
      <property name="tokenrate" value="1"/>
      <property name="direction" value="in"/>
      <property name="mathtype" value="complex"/>
      <property name="datatype" value="float"/>
      <property name="tokentype" value="scalar"/>
      <property name="traffictype" value="stream"/>
    </port>
    <port name="PE_2_1_Ele_in461">
      <property name="assemblyfactor_p" value="1"/>
      <property name="tokenrate" value="1"/>
      <property name="direction" value="in"/>
      <property name="mathtype" value="complex"/>
      <property name="datatype" value="float"/>
      <property name="tokentype" value="scalar"/>
      <property name="traffictype" value="stream"/>
    </port>
    <port name="PE_2_1_Ele_in561">
      <property name="assemblyfactor_p" value="1"/>
      <property name="tokenrate" value="1"/>
      <property name="direction" value="in"/>
      <property name="mathtype" value="complex"/>
      <property name="datatype" value="float"/>
      <property name="tokentype" value="scalar"/>
      <property name="traffictype" value="stream"/>
    </port>
    <port name="PE_2_1_Ele_in171">
      <property name="assemblyfactor_p" value="1"/>
      <property name="tokenrate" value="1"/>
      <property name="direction" value="in"/>
      <property name="mathtype" value="real"/>
      <property name="datatype" value="float"/>
      <property name="tokentype" value="vector">
        <property name="size" value="1"/>
      </property>
      <property name="traffictype" value="stream"/>
    </port>
    <port name="PE_2_1_Ele_in271">
      <property name="assemblyfactor_p" value="1"/>
      <property name="tokenrate" value="1"/>
      <property name="direction" value="in"/>
      <property name="mathtype" value="complex"/>
      <property name="datatype" value="float"/>
      <property name="tokentype" value="scalar"/>
      <property name="traffictype" value="stream"/>
    </port>
    <port name="PE_2_1_Ele_in371">
      <property name="assemblyfactor_p" value="1"/>
      <property name="tokenrate" value="1"/>
      <property name="direction" value="in"/>
      <property name="mathtype" value="complex"/>
      <property name="datatype" value="float"/>
      <property name="tokentype" value="scalar"/>
      <property name="traffictype" value="stream"/>
    </port>
    <port name="PE_2_1_Ele_in471">
      <property name="assemblyfactor_p" value="1"/>
      <property name="tokenrate" value="1"/>
      <property name="direction" value="in"/>
      <property name="mathtype" value="complex"/>
      <property name="datatype" value="float"/>
      <property name="tokentype" value="scalar"/>
      <property name="traffictype" value="stream"/>
    </port>
    <port name="PE_2_1_Ele_in571">
      <property name="assemblyfactor_p" value="1"/>
      <property name="tokenrate" value="1"/>
      <property name="direction" value="in"/>
      <property name="mathtype" value="complex"/>
      <property name="datatype" value="float"/>
      <property name="tokentype" value="scalar"/>
      <property name="traffictype" value="stream"/>
    </port>
    <port name="PE_2_1_Ele_in181">
      <property name="assemblyfactor_p" value="1"/>
      <property name="tokenrate" value="1"/>
      <property name="direction" value="in"/>
      <property name="mathtype" value="real"/>
      <property name="datatype" value="float"/>
      <property name="tokentype" value="vector">
        <property name="size" value="1"/>
      </property>
      <property name="traffictype" value="stream"/>
    </port>
    <port name="PE_2_1_Ele_in281">
      <property name="assemblyfactor_p" value="1"/>
      <property name="tokenrate" value="1"/>
      <property name="direction" value="in"/>
      <property name="mathtype" value="complex"/>
      <property name="datatype" value="float"/>
      <property name="tokentype" value="scalar"/>
      <property name="traffictype" value="stream"/>
    </port>
    <port name="PE_2_1_Ele_in381">
      <property name="assemblyfactor_p" value="1"/>
      <property name="tokenrate" value="1"/>
      <property name="direction" value="in"/>
      <property name="mathtype" value="complex"/>
      <property name="datatype" value="float"/>
      <property name="tokentype" value="scalar"/>
      <property name="traffictype" value="stream"/>
    </port>
    <port name="PE_2_1_Ele_in481">
      <property name="assemblyfactor_p" value="1"/>
      <property name="tokenrate" value="1"/>
      <property name="direction" value="in"/>
      <property name="mathtype" value="complex"/>
      <property name="datatype" value="float"/>
      <property name="tokentype" value="scalar"/>
      <property name="traffictype" value="stream"/>
    </port>
    <port name="PE_2_1_Ele_in581">
      <property name="assemblyfactor_p" value="1"/>
      <property name="tokenrate" value="1"/>
      <property name="direction" value="in"/>
      <property name="mathtype" value="complex"/>
      <property name="datatype" value="float"/>
      <property name="tokentype" value="scalar"/>
      <property name="traffictype" value="stream"/>
    </port>
    <port name="PE_2_1_Ele_in191">
      <property name="assemblyfactor_p" value="1"/>
      <property name="tokenrate" value="1"/>
      <property name="direction" value="in"/>
      <property name="mathtype" value="real"/>
      <property name="datatype" value="float"/>
      <property name="tokentype" value="vector">
        <property name="size" value="1"/>
      </property>
      <property name="traffictype" value="stream"/>
    </port>
    <port name="PE_2_1_Ele_in291">
      <property name="assemblyfactor_p" value="1"/>
      <property name="tokenrate" value="1"/>
      <property name="direction" value="in"/>
      <property name="mathtype" value="complex"/>
      <property name="datatype" value="float"/>
      <property name="tokentype" value="scalar"/>
      <property name="traffictype" value="stream"/>
    </port>
    <port name="PE_2_1_Ele_in391">
      <property name="assemblyfactor_p" value="1"/>
      <property name="tokenrate" value="1"/>
      <property name="direction" value="in"/>
      <property name="mathtype" value="complex"/>
      <property name="datatype" value="float"/>
      <property name="tokentype" value="scalar"/>
      <property name="traffictype" value="stream"/>
    </port>
    <port name="PE_2_1_Ele_in491">
      <property name="assemblyfactor_p" value="1"/>
      <property name="tokenrate" value="1"/>
      <property name="direction" value="in"/>
      <property name="mathtype" value="complex"/>
      <property name="datatype" value="float"/>
      <property name="tokentype" value="scalar"/>
      <property name="traffictype" value="stream"/>
    </port>
    <port name="PE_2_1_Ele_in591">
      <property name="assemblyfactor_p" value="1"/>
      <property name="tokenrate" value="1"/>
      <property name="direction" value="in"/>
      <property name="mathtype" value="complex"/>
      <property name="datatype" value="float"/>
      <property name="tokentype" value="scalar"/>
      <property name="traffictype" value="stream"/>
    </port>
    <port name="PE_2_1_Ele_in1101">
      <property name="assemblyfactor_p" value="1"/>
      <property name="tokenrate" value="1"/>
      <property name="direction" value="in"/>
      <property name="mathtype" value="real"/>
      <property name="datatype" value="float"/>
      <property name="tokentype" value="vector">
        <property name="size" value="1"/>
      </property>
      <property name="traffictype" value="stream"/>
    </port>
    <port name="PE_2_1_Ele_in2101">
      <property name="assemblyfactor_p" value="1"/>
      <property name="tokenrate" value="1"/>
      <property name="direction" value="in"/>
      <property name="mathtype" value="complex"/>
      <property name="datatype" value="float"/>
      <property name="tokentype" value="scalar"/>
      <property name="traffictype" value="stream"/>
    </port>
    <port name="PE_2_1_Ele_in3101">
      <property name="assemblyfactor_p" value="1"/>
      <property name="tokenrate" value="1"/>
      <property name="direction" value="in"/>
      <property name="mathtype" value="complex"/>
      <property name="datatype" value="float"/>
      <property name="tokentype" value="scalar"/>
      <property name="traffictype" value="stream"/>
    </port>
    <port name="PE_2_1_Ele_in4101">
      <property name="assemblyfactor_p" value="1"/>
      <property name="tokenrate" value="1"/>
      <property name="direction" value="in"/>
      <property name="mathtype" value="complex"/>
      <property name="datatype" value="float"/>
      <property name="tokentype" value="scalar"/>
      <property name="traffictype" value="stream"/>
    </port>
    <port name="PE_2_1_Ele_in5101">
      <property name="assemblyfactor_p" value="1"/>
      <property name="tokenrate" value="1"/>
      <property name="direction" value="in"/>
      <property name="mathtype" value="complex"/>
      <property name="datatype" value="float"/>
      <property name="tokentype" value="scalar"/>
      <property name="traffictype" value="stream"/>
    </port>
    <port name="PE_2_1_Ele_in1111">
      <property name="assemblyfactor_p" value="1"/>
      <property name="tokenrate" value="1"/>
      <property name="direction" value="in"/>
      <property name="mathtype" value="real"/>
      <property name="datatype" value="float"/>
      <property name="tokentype" value="vector">
        <property name="size" value="1"/>
      </property>
      <property name="traffictype" value="stream"/>
    </port>
    <port name="PE_2_1_Ele_in2111">
      <property name="assemblyfactor_p" value="1"/>
      <property name="tokenrate" value="1"/>
      <property name="direction" value="in"/>
      <property name="mathtype" value="complex"/>
      <property name="datatype" value="float"/>
      <property name="tokentype" value="scalar"/>
      <property name="traffictype" value="stream"/>
    </port>
    <port name="PE_2_1_Ele_in3111">
      <property name="assemblyfactor_p" value="1"/>
      <property name="tokenrate" value="1"/>
      <property name="direction" value="in"/>
      <property name="mathtype" value="complex"/>
      <property name="datatype" value="float"/>
      <property name="tokentype" value="scalar"/>
      <property name="traffictype" value="stream"/>
    </port>
    <port name="PE_2_1_Ele_in4111">
      <property name="assemblyfactor_p" value="1"/>
      <property name="tokenrate" value="1"/>
      <property name="direction" value="in"/>
      <property name="mathtype" value="complex"/>
      <property name="datatype" value="float"/>
      <property name="tokentype" value="scalar"/>
      <property name="traffictype" value="stream"/>
    </port>
    <port name="PE_2_1_Ele_in5111">
      <property name="assemblyfactor_p" value="1"/>
      <property name="tokenrate" value="1"/>
      <property name="direction" value="in"/>
      <property name="mathtype" value="complex"/>
      <property name="datatype" value="float"/>
      <property name="tokentype" value="scalar"/>
      <property name="traffictype" value="stream"/>
    </port>
    <port name="PE_2_1_Ele_in1121">
      <property name="assemblyfactor_p" value="1"/>
      <property name="tokenrate" value="1"/>
      <property name="direction" value="in"/>
      <property name="mathtype" value="real"/>
      <property name="datatype" value="float"/>
      <property name="tokentype" value="vector">
        <property name="size" value="1"/>
      </property>
      <property name="traffictype" value="stream"/>
    </port>
    <port name="PE_2_1_Ele_in2121">
      <property name="assemblyfactor_p" value="1"/>
      <property name="tokenrate" value="1"/>
      <property name="direction" value="in"/>
      <property name="mathtype" value="complex"/>
      <property name="datatype" value="float"/>
      <property name="tokentype" value="scalar"/>
      <property name="traffictype" value="stream"/>
    </port>
    <port name="PE_2_1_Ele_in3121">
      <property name="assemblyfactor_p" value="1"/>
      <property name="tokenrate" value="1"/>
      <property name="direction" value="in"/>
      <property name="mathtype" value="complex"/>
      <property name="datatype" value="float"/>
      <property name="tokentype" value="scalar"/>
      <property name="traffictype" value="stream"/>
    </port>
    <port name="PE_2_1_Ele_in4121">
      <property name="assemblyfactor_p" value="1"/>
      <property name="tokenrate" value="1"/>
      <property name="direction" value="in"/>
      <property name="mathtype" value="complex"/>
      <property name="datatype" value="float"/>
      <property name="tokentype" value="scalar"/>
      <property name="traffictype" value="stream"/>
    </port>
    <port name="PE_2_1_Ele_in5121">
      <property name="assemblyfactor_p" value="1"/>
      <property name="tokenrate" value="1"/>
      <property name="direction" value="in"/>
      <property name="mathtype" value="complex"/>
      <property name="datatype" value="float"/>
      <property name="tokentype" value="scalar"/>
      <property name="traffictype" value="stream"/>
    </port>
    <port name="PE_2_1_Ele_in1131">
      <property name="assemblyfactor_p" value="1"/>
      <property name="tokenrate" value="1"/>
      <property name="direction" value="in"/>
      <property name="mathtype" value="real"/>
      <property name="datatype" value="float"/>
      <property name="tokentype" value="vector">
        <property name="size" value="1"/>
      </property>
      <property name="traffictype" value="stream"/>
    </port>
    <port name="PE_2_1_Ele_in2131">
      <property name="assemblyfactor_p" value="1"/>
      <property name="tokenrate" value="1"/>
      <property name="direction" value="in"/>
      <property name="mathtype" value="complex"/>
      <property name="datatype" value="float"/>
      <property name="tokentype" value="scalar"/>
      <property name="traffictype" value="stream"/>
    </port>
    <port name="PE_2_1_Ele_in3131">
      <property name="assemblyfactor_p" value="1"/>
      <property name="tokenrate" value="1"/>
      <property name="direction" value="in"/>
      <property name="mathtype" value="complex"/>
      <property name="datatype" value="float"/>
      <property name="tokentype" value="scalar"/>
      <property name="traffictype" value="stream"/>
    </port>
    <port name="PE_2_1_Ele_in4131">
      <property name="assemblyfactor_p" value="1"/>
      <property name="tokenrate" value="1"/>
      <property name="direction" value="in"/>
      <property name="mathtype" value="complex"/>
      <property name="datatype" value="float"/>
      <property name="tokentype" value="scalar"/>
      <property name="traffictype" value="stream"/>
    </port>
    <port name="PE_2_1_Ele_in5131">
      <property name="assemblyfactor_p" value="1"/>
      <property name="tokenrate" value="1"/>
      <property name="direction" value="in"/>
      <property name="mathtype" value="complex"/>
      <property name="datatype" value="float"/>
      <property name="tokentype" value="scalar"/>
      <property name="traffictype" value="stream"/>
    </port>
    <port name="PE_2_1_Ele_in1141">
      <property name="assemblyfactor_p" value="1"/>
      <property name="tokenrate" value="1"/>
      <property name="direction" value="in"/>
      <property name="mathtype" value="real"/>
      <property name="datatype" value="float"/>
      <property name="tokentype" value="vector">
        <property name="size" value="1"/>
      </property>
      <property name="traffictype" value="stream"/>
    </port>
    <port name="PE_2_1_Ele_in2141">
      <property name="assemblyfactor_p" value="1"/>
      <property name="tokenrate" value="1"/>
      <property name="direction" value="in"/>
      <property name="mathtype" value="complex"/>
      <property name="datatype" value="float"/>
      <property name="tokentype" value="scalar"/>
      <property name="traffictype" value="stream"/>
    </port>
    <port name="PE_2_1_Ele_in3141">
      <property name="assemblyfactor_p" value="1"/>
      <property name="tokenrate" value="1"/>
      <property name="direction" value="in"/>
      <property name="mathtype" value="complex"/>
      <property name="datatype" value="float"/>
      <property name="tokentype" value="scalar"/>
      <property name="traffictype" value="stream"/>
    </port>
    <port name="PE_2_1_Ele_in4141">
      <property name="assemblyfactor_p" value="1"/>
      <property name="tokenrate" value="1"/>
      <property name="direction" value="in"/>
      <property name="mathtype" value="complex"/>
      <property name="datatype" value="float"/>
      <property name="tokentype" value="scalar"/>
      <property name="traffictype" value="stream"/>
    </port>
    <port name="PE_2_1_Ele_in5141">
      <property name="assemblyfactor_p" value="1"/>
      <property name="tokenrate" value="1"/>
      <property name="direction" value="in"/>
      <property name="mathtype" value="complex"/>
      <property name="datatype" value="float"/>
      <property name="tokentype" value="scalar"/>
      <property name="traffictype" value="stream"/>
    </port>
    <port name="PE_2_1_Ele_in1151">
      <property name="assemblyfactor_p" value="1"/>
      <property name="tokenrate" value="1"/>
      <property name="direction" value="in"/>
      <property name="mathtype" value="real"/>
      <property name="datatype" value="float"/>
      <property name="tokentype" value="vector">
        <property name="size" value="1"/>
      </property>
      <property name="traffictype" value="stream"/>
    </port>
    <port name="PE_2_1_Ele_in2151">
      <property name="assemblyfactor_p" value="1"/>
      <property name="tokenrate" value="1"/>
      <property name="direction" value="in"/>
      <property name="mathtype" value="complex"/>
      <property name="datatype" value="float"/>
      <property name="tokentype" value="scalar"/>
      <property name="traffictype" value="stream"/>
    </port>
    <port name="PE_2_1_Ele_in3151">
      <property name="assemblyfactor_p" value="1"/>
      <property name="tokenrate" value="1"/>
      <property name="direction" value="in"/>
      <property name="mathtype" value="complex"/>
      <property name="datatype" value="float"/>
      <property name="tokentype" value="scalar"/>
      <property name="traffictype" value="stream"/>
    </port>
    <port name="PE_2_1_Ele_in4151">
      <property name="assemblyfactor_p" value="1"/>
      <property name="tokenrate" value="1"/>
      <property name="direction" value="in"/>
      <property name="mathtype" value="complex"/>
      <property name="datatype" value="float"/>
      <property name="tokentype" value="scalar"/>
      <property name="traffictype" value="stream"/>
    </port>
    <port name="PE_2_1_Ele_in5151">
      <property name="assemblyfactor_p" value="1"/>
      <property name="tokenrate" value="1"/>
      <property name="direction" value="in"/>
      <property name="mathtype" value="complex"/>
      <property name="datatype" value="float"/>
      <property name="tokentype" value="scalar"/>
      <property name="traffictype" value="stream"/>
    </port>
    <port name="PE_2_1_Ele_in1161">
      <property name="assemblyfactor_p" value="1"/>
      <property name="tokenrate" value="1"/>
      <property name="direction" value="in"/>
      <property name="mathtype" value="real"/>
      <property name="datatype" value="float"/>
      <property name="tokentype" value="vector">
        <property name="size" value="1"/>
      </property>
      <property name="traffictype" value="stream"/>
    </port>
    <port name="PE_2_1_Ele_in2161">
      <property name="assemblyfactor_p" value="1"/>
      <property name="tokenrate" value="1"/>
      <property name="direction" value="in"/>
      <property name="mathtype" value="complex"/>
      <property name="datatype" value="float"/>
      <property name="tokentype" value="scalar"/>
      <property name="traffictype" value="stream"/>
    </port>
    <port name="PE_2_1_Ele_in3161">
      <property name="assemblyfactor_p" value="1"/>
      <property name="tokenrate" value="1"/>
      <property name="direction" value="in"/>
      <property name="mathtype" value="complex"/>
      <property name="datatype" value="float"/>
      <property name="tokentype" value="scalar"/>
      <property name="traffictype" value="stream"/>
    </port>
    <port name="PE_2_1_Ele_in4161">
      <property name="assemblyfactor_p" value="1"/>
      <property name="tokenrate" value="1"/>
      <property name="direction" value="in"/>
      <property name="mathtype" value="complex"/>
      <property name="datatype" value="float"/>
      <property name="tokentype" value="scalar"/>
      <property name="traffictype" value="stream"/>
    </port>
    <port name="PE_2_1_Ele_in5161">
      <property name="assemblyfactor_p" value="1"/>
      <property name="tokenrate" value="1"/>
      <property name="direction" value="in"/>
      <property name="mathtype" value="complex"/>
      <property name="datatype" value="float"/>
      <property name="tokentype" value="scalar"/>
      <property name="traffictype" value="stream"/>
    </port>
    <port name="PE_2_1_Ele_out1">
      <property name="assemblyfactor_p" value="1"/>
      <property name="tokenrate" value="1"/>
      <property name="direction" value="out"/>
      <property name="mathtype" value="complex"/>
      <property name="datatype" value="float"/>
      <property name="tokentype" value="vector">
        <property name="size" value="4"/>
      </property>
      <property name="traffictype" value="stream"/>
    </port>
    <port name="PE_2_1_Ele_out12">
      <property name="assemblyfactor_p" value="1"/>
      <property name="tokenrate" value="1"/>
      <property name="direction" value="out"/>
      <property name="mathtype" value="complex"/>
      <property name="datatype" value="float"/>
      <property name="tokentype" value="vector">
        <property name="size" value="4"/>
      </property>
      <property name="traffictype" value="stream"/>
    </port>
  </interface>
</entity>

